Metadata-Version: 1.0
Name: sentence-pass
Version: 0.1
Summary: A class to generate password from a sentence
Home-page: UNKNOWN
Author: Huyen Le
Author-email: UNKNOWN
License: UNKNOWN
Platform: UNKNOWN
